turgnamh/__init__.py
turgnamh/py.typed
turgnamh/settings.py
turgnamh/core/__init__.py
turgnamh/core/experiment.py
turgnamh/utils/printing.py
turgnamh-0.1.1.dist-info/METADATA
turgnamh-0.1.1.dist-info/WHEEL
turgnamh-0.1.1.dist-info/RECORD
